vplus_constants/__init__.py
vplus_constants/offline_results/__init__.py
vplus_constants/offline_results/constant.py
vplus_constant_module-0.1.1.dist-info/METADATA
vplus_constant_module-0.1.1.dist-info/WHEEL
vplus_constant_module-0.1.1.dist-info/top_level.txt
vplus_constant_module-0.1.1.dist-info/RECORD
