Metadata-Version: 2.1
Name: vplus-constant-module
Version: 0.1.1
Summary: Vdb constant models
Home-page: https://mnc-repo.mncdigital.com/ai-team/vision_plus/visionplus-constant
Author: AI Teams
Author-email: ferdina.kusumah@mncgroup.com
License: MIT
Platform: UNKNOWN
Classifier: License :: OSI Approved :: MIT License
Classifier: Programming Language :: Python :: 3
Classifier: Programming Language :: Python :: 3.7
Classifier: Programming Language :: Python :: 3.8
Classifier: Programming Language :: Python :: 3.9
Requires-Dist: pydantic (==1.9.0)
